jupytergis_lab/__init__.py
jupytergis_lab/_version.py
jupytergis_lab/notebook/__init__.py
jupytergis_lab/notebook/explore.py
jupytergis_lab/notebook/gis_document.py
jupytergis_lab/notebook/utils.py
jupytergis_lab/notebook/y_connector.py
jupytergis_lab/notebook/tests/__init__.py
jupytergis_lab/notebook/tests/test_api.py
jupytergis_lab-0.11.1.data/data/share/jupyter/labextensions/@jupytergis/jupytergis-lab/package.json
jupytergis_lab-0.11.1.data/data/share/jupyter/labextensions/@jupytergis/jupytergis-lab/static/432.9d5c05b33142f523620a.js
jupytergis_lab-0.11.1.data/data/share/jupyter/labextensions/@jupytergis/jupytergis-lab/static/484.9e9305472a02e923949c.js
jupytergis_lab-0.11.1.data/data/share/jupyter/labextensions/@jupytergis/jupytergis-lab/static/remoteEntry.eff768b6c1a62cde9f0a.js
jupytergis_lab-0.11.1.data/data/share/jupyter/labextensions/@jupytergis/jupytergis-lab/static/style.js
jupytergis_lab-0.11.1.data/data/share/jupyter/labextensions/@jupytergis/jupytergis-lab/static/third-party-licenses.json
jupytergis_lab-0.11.1.data/data/share/jupyter/labextensions/@jupytergis/jupytergis-lab/install.json
jupytergis_lab-0.11.1.dist-info/METADATA
jupytergis_lab-0.11.1.dist-info/WHEEL
jupytergis_lab-0.11.1.dist-info/licenses/LICENSE
jupytergis_lab-0.11.1.dist-info/RECORD
