Metadata-Version: 2.4
Name: jupytergis_lab
Version: 0.11.1
Dynamic: Keywords
Summary: JupyterGIS Lab extension.
Project-URL: Homepage, https://github.com/geojupyter/jupytergis
Project-URL: Bug Tracker, https://github.com/geojupyter/jupytergis/issues
Project-URL: Repository, https://github.com/geojupyter/jupytergis.git
Author: JupyterGIS contributors
License: BSD 3-Clause License
License-File: LICENSE
Classifier: Framework :: Jupyter
Classifier: Framework :: Jupyter :: JupyterLab
Classifier: Framework :: Jupyter :: JupyterLab :: 4
Classifier: Framework :: Jupyter :: JupyterLab :: Extensions
Classifier: Framework :: Jupyter :: JupyterLab :: Extensions :: Prebuilt
Classifier: License :: OSI Approved :: BSD License
Classifier: Programming Language :: Python
Classifier: Programming Language :: Python :: 3
Classifier: Programming Language :: Python :: 3.10
Classifier: Programming Language :: Python :: 3.11
Classifier: Programming Language :: Python :: 3.12
Classifier: Programming Language :: Python :: 3.13
Classifier: Programming Language :: Python :: 3.14
Classifier: Topic :: Scientific/Engineering :: GIS
Requires-Python: >=3.10
Requires-Dist: comm<0.2.0,>=0.1.2
Requires-Dist: jupyter-ydoc<4,>=2
Requires-Dist: jupytergis-core<1,>=0.1.0
Requires-Dist: pydantic<3,>=2
Requires-Dist: requests
Requires-Dist: sidecar>=0.7.0
Requires-Dist: yjs-widgets<0.5,>=0.4
Requires-Dist: ypywidgets<0.10.0,>=0.9.0
